LICENSE
MANIFEST.in
README.md
setup.cfg
setup.py
K2ephem/K2ephem.py
K2ephem/__init__.py
K2ephem/version.py
K2ephem.egg-info/PKG-INFO
K2ephem.egg-info/SOURCES.txt
K2ephem.egg-info/dependency_links.txt
K2ephem.egg-info/requires.txt
K2ephem.egg-info/top_level.txt
scripts/K2ephem