Metadata-Version: 1.1
Name: K2ephem
Version: 1.3.0
Summary: Check if a Solar System object is (or was) observable by NASA's K2 mission. This command will query JPL/Horizons to find out.
Home-page: https://github.com/KeplerGO/K2ephem
Author: Geert Barentsen
Author-email: hello@geert.io
License: UNKNOWN
Platform: UNKNOWN
Classifier: Development Status :: 5 - Production/Stable
Classifier: License :: OSI Approved :: MIT License
Classifier: Operating System :: OS Independent
Classifier: Programming Language :: Python
Classifier: Intended Audience :: Science/Research
Classifier: Topic :: Scientific/Engineering :: Astronomy
